{
	"info": {
		"_postman_id": "8b81ce75-8936-4aa7-bdeb-fdb213235e55",
		"name": "instagram-clone-project",
		"schema": "https://schema.getpostman.com/json/collection/v2.1.0/collection.json"
	},
	"item": [
		{
			"name": "localhost:8080/user/join",
			"request": {
				"method": "POST",
				"header": [],
				"body": {
					"mode": "raw",
					"raw": "{\n    \"username\" : \"westssun\",\n    \"password\" : \"123123\",\n    \"email\" : \"test@test.cop\",\n    \"name\" : \"kimseohae\"\n}",
					"options": {
						"raw": {
							"language": "json"
						}
					}
				},
				"url": {
					"raw": "localhost:8080/user/join",
					"host": [
						"localhost"
					],
					"port": "8080",
					"path": [
						"user",
						"join"
					]
				}
			},
			"response": []
		},
		{
			"name": "localhost:8080/login",
			"request": {
				"method": "POST",
				"header": [],
				"body": {
					"mode": "raw",
					"raw": "{\n    \"username\" : \"westssun\",\n    \"password\" : \"123123\"\n}",
					"options": {
						"raw": {
							"language": "json"
						}
					}
				},
				"url": {
					"raw": "localhost:8080/login",
					"host": [
						"localhost"
					],
					"port": "8080",
					"path": [
						"login"
					]
				}
			},
			"response": []
		},
		{
			"name": "localhost:8080/user/load",
			"protocolProfileBehavior": {
				"disableBodyPruning": true
			},
			"request": {
				"method": "GET",
				"header": [
					{
						"key": "Authorization",
						"value": "Bearer eyJ0eXAiOiJKV1QiLCJhbGciOiJIUzUxMiJ9.eyJzdWIiOiJ3ZXN0c3N1biIsImlkIjoxLCJleHAiOjE2NDA0MTUxNDYsInVzZXJuYW1lIjoid2VzdHNzdW4ifQ.IxqN17rsYzrBBQRH35DvvH2HuGbJ658QS0ybqcuZyjtl51Ny9annREoBr6E25pD1NuL2RX2_kln07azi1BZFgQ",
						"type": "text"
					}
				],
				"body": {
					"mode": "raw",
					"raw": "",
					"options": {
						"raw": {
							"language": "json"
						}
					}
				},
				"url": {
					"raw": "localhost:8080/user/load",
					"host": [
						"localhost"
					],
					"port": "8080",
					"path": [
						"user",
						"load"
					]
				}
			},
			"response": []
		}
	]
}